[
  {
    "Part Number": "11",
    "Part Code": "A0860011",
    "Issue": "One preceding road name is illegible",
    "Review Type": "Illegible / insufficient OCR",
    "Raw Kannada OCR": "2.ಕತ್ರದ ವಿವರಗಳು\nಭಾಗದ ಪ್ರದೇಶ:\n1. sodA eel, ರಸ್ತೆ, WY AOA, ಸುಬ್ಬರಾಜು ರಸ್ತೆ, 2.\nಮೆಂಕಟಿರಾಂ ಬಡಾವಣೆ, 3. ಮುಬಿಗಾ ಬಡಾವಣೆ\nಭಾಗದ ವರ್ಗೀಕರಣ: ನಗರ | ಈ ಭಾಗದಲ್ಲಿನ ಸಹಾಯಕ\nಮತಗಟ್ಟೆಗಳ ಸಂಖ್ಯೆ:\n3. ಮತಗಟ್ಟೆಯ ವಿವರಗಳು",
    "Source Image": "A0860011.png",
    "Official PDF URL": "https://ceo.karnataka.gov.in/uploads/BBMP/AC%2086/A0860011.pdf"
  },
  {
    "Part Number": "23",
    "Part Code": "A0860023",
    "Issue": "Illegible / insufficient OCR",
    "Review Type": "Illegible / insufficient OCR",
    "Raw Kannada OCR": "2.ಕತ್ರದ ವಿವರಗಳು\nಭಾಗದ ಪ್ರದೇಶ:\n1. Binnie\nಭಾಗದ ವರ್ಗೀಕರಣ: ನಗರ | ಈ ಭಾಗದಲ್ಲಿನ ಸಹಾಯಕ\nಮತಗಟ್ಟೆಗಳ ಸಂಖ್ಯೆ:\n3. ಮತಗಟ್ಟೆಯ ವಿವರಗಳು",
    "Source Image": "A0860023.png",
    "Official PDF URL": "https://ceo.karnataka.gov.in/uploads/BBMP/AC%2086/A0860023.pdf"
  },
  {
    "Part Number": "24",
    "Part Code": "A0860024",
    "Issue": "One additional layout name is illegible",
    "Review Type": "Illegible / insufficient OCR",
    "Raw Kannada OCR": "2.ಕೇತದ ವಿವರಗಳು\nಭಾಗದ ಪ್ರದೇಶ:\n1. ಹೀರಾ ಚಂದ ಬಡಾವಣೆ\n2, momen Fecal) Blaine\nಭಾಗದ ವರ್ಗೀಕರಣ: ನಗರ | ಈ ಭಾಗದಲಿನ ಸಹಾಯಕ\nಮತಗಟ್ಟೆಗಳ ಸಂಖ್ಯೆ:\n3. ಮತಗಟ್ಟೆಯ ವಿವರಗಳು",
    "Source Image": "A0860024.png",
    "Official PDF URL": "https://ceo.karnataka.gov.in/uploads/BBMP/AC%2086/A0860024.pdf"
  },
  {
    "Part Number": "29",
    "Part Code": "A0860029",
    "Issue": "House-number section; remaining OCR insufficient",
    "Review Type": "Readable but unresolved / geocode not confirmed",
    "Raw Kannada OCR": "2.ಕತ್ರದ ವಿವರಗಳು\nಭಾಗದ ಪ್ರದೇಶ:\n1. ದೋಡ್ಡ model 1-88\nಭಾಗದ ವರ್ಗೀಕರಣ: ನಗರ | ಈ ಭಾಗದಲ್ಲಿನ ಸಹಾಯಕ\nಮತಗಟ್ಟೆಗಳ ಸಂಖ್ಯೆ:\n3. ಮತಗಟ್ಟೆಯ ವಿವರಗಳು",
    "Source Image": "A0860029.png",
    "Official PDF URL": "https://ceo.karnataka.gov.in/uploads/BBMP/AC%2086/A0860029.pdf"
  },
  {
    "Part Number": "30",
    "Part Code": "A0860030",
    "Issue": "One compound-road name is unclear",
    "Review Type": "Readable but unresolved / geocode not confirmed",
    "Raw Kannada OCR": "2.ಕೇತದ ವಿವರಗಳು\nಭಾಗದ ಪ್ರದೇಶ:\n\n1. dex ಕಾಂಪಬಲ್‌* ರಸ್ತೆ. 2. ರಾಮಕೃಷ್ಣಪ್ಪ ರಸ್ತೆ. 3.\nದಾಸಪ್ಪ ಲೇಔಟ್‌, 4. ಧನರಾಜ್‌್‌ ಕಠಾರಿಯ ರಸ್ತೆ, 5. ಪೂಲ್‌\nಚಂದ್‌ ಲೇಔಟ್‌, 6. ಅಬ್ದುಲ್‌ ಹಷೇಜ್‌್‌ ರಸೆ(ಎಡಭಾಗ), 7.\nಗೊಂಡಾಲ್‌ಸ ಮಹಾರಾಜ್‌ ಲೇಔಟ್‌\n\nಭಾಗದ ವರ್ಗೀಕರಣ: ನಗರ | ಈ ಭಾಗದಲಿನ ಸಹಾಯಕ\n\nಮತಗಟ್ಟೆಗಳ ಸ೦ಖ್ಯೆ:",
    "Source Image": "A0860030.png",
    "Official PDF URL": "https://ceo.karnataka.gov.in/uploads/BBMP/AC%2086/A0860030.pdf"
  },
  {
    "Part Number": "31",
    "Part Code": "A0860031",
    "Issue": "One garden name is unresolved",
    "Review Type": "Readable but unresolved / geocode not confirmed",
    "Raw Kannada OCR": "2.ಕೇತದ ವಿವರಗಳು\nಭಾಗದ ಪ್ರದೇಶ:\n\n1. Gears 2063 89-139 2. ಗೊೋಳವಿ೦ಂದಪ್ಹ ಗಾರ್ಡನ್‌ 1-17, 3.\nಗ್ಪೇಪ್‌ಕ ಗಾರ್ಡನ್‌ 1-30, 4. ಧನರಾಜ್‌್‌ ಹೀರಾ ಚಂದ್‌\nಲೇಔಟ್‌\n\nಭಾಗದ ವರ್ಗೀಕರಣ: ನಗರ | ಈ ಭಾಗದಲಿನ ಸಹಾಯಕ\n\nಮತಗಟ್ಟೆಗಳ ಸ೦ಖ್ಯೆ:\nFy ds ded a",
    "Source Image": "A0860031.png",
    "Official PDF URL": "https://ceo.karnataka.gov.in/uploads/BBMP/AC%2086/A0860031.pdf"
  },
  {
    "Part Number": "32",
    "Part Code": "A0860032",
    "Issue": "One garden name is unresolved",
    "Review Type": "Readable but unresolved / geocode not confirmed",
    "Raw Kannada OCR": "2.ಕೇತದ ವಿವರಗಳು\nಭಾಗದ ಪ್ರದೇಶ:\n1. Gar 2063 68-219/1, 2. ಮುಬಿಯೆಲ್ಲಪ್ಪ ತೋಟಿ 1-33,\n3. Sate tial, ಗಾರ್ಡನ್‌ 1-40\nಭಾಗದ ವರ್ಗೀಕರಣ: ನಗರ | ಈ ಭಾಗದಲಿನ ಸಹಾಯಕ\nಮತಗಟ್ಟೆಗಳ ಸಂಖ್ಯೆ:\n3. ಮತಗಟ್ಟೆಯ ವಿವರಗಳು",
    "Source Image": "A0860032.png",
    "Official PDF URL": "https://ceo.karnataka.gov.in/uploads/BBMP/AC%2086/A0860032.pdf"
  },
  {
    "Part Number": "38",
    "Part Code": "A0860038",
    "Issue": "Locality OCR appears to reference Kallahalli; needs confirmation",
    "Review Type": "Readable but unresolved / geocode not confirmed",
    "Raw Kannada OCR": "2.ಕೇತದ ವಿವರಗಳು\nಭಾಗದ ಪ್ರದೇಶ:\n1.2.8.0. ಕ್ರಾರ್ಟಿರಸ ಕಲಳಿ 2. ಕೆಮಬ್ಬಿಂಗಸಟಿವ್‌ OA\nಭಾಗದ ವರ್ಗೀಕರಣ: ನಗರ | ಈ ಭಾಗದಲಿನ ಸಹಾಯಕ\nಮತಗಟ್ಟೆಗಳ ಸಂಖ್ಯೆ:\n3. ಮತಗಟ್ಟೆಯ ವಿವರಗಳು",
    "Source Image": "A0860038.png",
    "Official PDF URL": "https://ceo.karnataka.gov.in/uploads/BBMP/AC%2086/A0860038.pdf"
  },
  {
    "Part Number": "43",
    "Part Code": "A0860043",
    "Issue": "Source name clear; current spelling/geocode needs confirmation",
    "Review Type": "Readable but unresolved / geocode not confirmed",
    "Raw Kannada OCR": "2.ಕತ್ರದ ವಿವರಗಳು\nಭಾಗದ ಪ್ರದೇಶ:\nಕದಿರಯ್ಯವಪಾ;\nಭಾಗದ ವರ್ಗೀಕರಣ: ನಗರ | ಈ ಭಾಗದಲ್ಲಿನ ಸಹಾಯಕ\nಮತಗಟ್ಟೆಗಳ ಸಂಖ್ಯೆ:\n3. ಮತಗಟ್ಟೆಯ ವಿವರಗಳು",
    "Source Image": "A0860043.png",
    "Official PDF URL": "https://ceo.karnataka.gov.in/uploads/BBMP/AC%2086/A0860043.pdf"
  },
  {
    "Part Number": "44",
    "Part Code": "A0860044",
    "Issue": "Source name clear; current spelling/geocode needs confirmation",
    "Review Type": "Readable but unresolved / geocode not confirmed",
    "Raw Kannada OCR": "2.ಕತ್ರದ ವಿವರಗಳು\nಭಾಗದ ಪ್ರದೇಶ:\nಕದಿರಯ್ಯವಪಾ;\nಭಾಗದ ವರ್ಗೀಕರಣ: ನಗರ | ಈ ಭಾಗದಲ್ಲಿನ ಸಹಾಯಕ\nಮತಗಟ್ಟೆಗಳ ಸಂಖ್ಯೆ:\n3. ಮತಗಟ್ಟೆಯ ವಿವರಗಳು",
    "Source Image": "A0860044.png",
    "Official PDF URL": "https://ceo.karnataka.gov.in/uploads/BBMP/AC%2086/A0860044.pdf"
  },
  {
    "Part Number": "45",
    "Part Code": "A0860045",
    "Issue": "Quarters designation is unclear",
    "Review Type": "Readable but unresolved / geocode not confirmed",
    "Raw Kannada OCR": "2.ಕೇತದ ವಿವರಗಳು\nಭಾಗದ ಪ್ರದೇಶ:\nಕೋಲಾರ OAL, 2ನೇ ದಿ ಕ್ಯಾರ್ಟಿಸ್‌\nಭಾಗದ ವರ್ಗೀಕರಣ: ನಗರ | ಈ ಭಾಗದಲಿನ ಸಹಾಯಕ\nಮತಗಟ್ಟೆಗಳ ಸಂಖ್ಯೆ:\n3. ಮತಗಟ್ಟೆಯ ವಿವರಗಳು",
    "Source Image": "A0860045.png",
    "Official PDF URL": "https://ceo.karnataka.gov.in/uploads/BBMP/AC%2086/A0860045.pdf"
  },
  {
    "Part Number": "55",
    "Part Code": "A0860055",
    "Issue": "One preceding road name is unresolved",
    "Review Type": "Readable but unresolved / geocode not confirmed",
    "Raw Kannada OCR": "2.ಕೇತದ ವಿವರಗಳು\n\nಭಾಗದ ಪ್ರದೇಶ:\n\n1. meto, ರಸ್ತೆ ಎ\n\n2. ಓ.ಪಿ.ಎಂ. ರಸ್ತೆ, 243-297\n\n3. ತಿಮ್ಮಯ್ಯರಸೆ 248-257,\n\nಭಾಗದ ವರ್ಗೀಕರಣ: ನಗರ | ಈ ಭಾಗದಲಿನ ಸಹಾಯಕ\n\nಮತಗಟ್ಟೆಗಳ ಸ೦ಖ್ಯೆ:\n\nFy ds ded a",
    "Source Image": "A0860055.png",
    "Official PDF URL": "https://ceo.karnataka.gov.in/uploads/BBMP/AC%2086/A0860055.pdf"
  },
  {
    "Part Number": "56",
    "Part Code": "A0860056",
    "Issue": "One numbered street is unresolved",
    "Review Type": "Readable but unresolved / geocode not confirmed",
    "Raw Kannada OCR": "2.ಕತ್ರದ ವಿವರಗಳು\nಭಾಗದ ಪ್ರದೇಶ:\n1. 808,04, 2-1\n2. ಕೂಕ್ಕರಸ್ತೆ 2-2\n3. ಟಿ.ನ೦ಂ. 1ನೇ ಬೀದಿ\nಭಾಗದ ವರ್ಗೀಕರಣ: ನಗರ | ಈ ಭಾಗದಲ್ಲಿನ ಸಹಾಯಕ\nಮತಗಟ್ಟೆಗಳ ಸ೦ಖ್ಯೆ:\nFy ds ded a",
    "Source Image": "A0860056.png",
    "Official PDF URL": "https://ceo.karnataka.gov.in/uploads/BBMP/AC%2086/A0860056.pdf"
  },
  {
    "Part Number": "65",
    "Part Code": "A0860065",
    "Issue": "Two numbered-street names are unresolved",
    "Review Type": "Readable but unresolved / geocode not confirmed",
    "Raw Kannada OCR": "2.ಕೇತದ ವಿವರಗಳು\nಭಾಗದ ಪ್ರದೇಶ:\n1. ಪೋಲೀಸ್‌ ವೈನ್‌ ಐ. ರಸ್ತೆ,2. 05, Ae, OM ರಸ್ತೆ, 3. Ao.\n2ವೇ ಬೀದಿ\nಭಾಗದ ವರ್ಗೀಕರಣ: ಸಗರ | ಈ ಭಾಗದಲ್ಲಿನ ಸಹಾಯಕ\nಮತಗಟ್ಟೆಗಳ ಸ೦ಖ್ಯೆ:\n3. ಮತಗಟ್ಟೆಯ ವಿವರಗಳು",
    "Source Image": "A0860065.png",
    "Official PDF URL": "https://ceo.karnataka.gov.in/uploads/BBMP/AC%2086/A0860065.pdf"
  },
  {
    "Part Number": "69",
    "Part Code": "A0860069",
    "Issue": "P No. 3rd Street 1st Cross",
    "Review Type": "Readable but unresolved / geocode not confirmed",
    "Raw Kannada OCR": "2.ಕೇತದ ವಿವರಗಳು\nಭಾಗದ ಪ್ರದೇಶ:\n\n1. AAO. 3ನೇ ಬೀದಿ, 1ನೇ ಕಾಸ್‌, 1-11\n2. 2 ನಂ.3ನೇ ಬೀದಿ, 1-18\n3, ಮಕಾನ ಕಾಂಪ್‌ೌಂಡ್‌ಸ\n4. ಸ್ಪ೧ ಬರಿಯಲ್‌ ಗೌ೦ಡ್‌ಸ\n\nಭಾಗದ ವರ್ಗೀಕರಣ: ನಗರ | ಈ ಭಾಗದಲಿನ ಸಹಾಯಕ\n\nಮತಗಟ್ಟೆಗಳ ಸಂಖ್ಯೆ:",
    "Source Image": "A0860069.png",
    "Official PDF URL": "https://ceo.karnataka.gov.in/uploads/BBMP/AC%2086/A0860069.pdf"
  },
  {
    "Part Number": "70",
    "Part Code": "A0860070",
    "Issue": "Requires source/map review",
    "Review Type": "Readable but unresolved / geocode not confirmed",
    "Raw Kannada OCR": "2.ಕತ್ರದ ವಿವರಗಳು\nಭಾಗದ ಪ್ರದೇಶ:\n1. ಮಕಾನ ರಸ್ತೆ 2. ಮಕಾನ ಕಾಂಪೌಂಡ್‌ 3. ALO Beers\nಗಕ್‌೦ಡ್‌ಸ ಭಾಗ\nಭಾಗದ ವರ್ಗೀಕರಣ: ನಗರ | ಈ ಭಾಗದಲಿನ ಸಹಾಯಕ\nಮತಗಟ್ಟೆಗಳ ಸಂಖ್ಯೆ:\n3. ಮತಗಟ್ಟೆಯ ವಿವರಗಳು",
    "Source Image": "A0860070.png",
    "Official PDF URL": "https://ceo.karnataka.gov.in/uploads/BBMP/AC%2086/A0860070.pdf"
  },
  {
    "Part Number": "74",
    "Part Code": "A0860074",
    "Issue": "One lettered-street cross is unresolved",
    "Review Type": "Readable but unresolved / geocode not confirmed",
    "Raw Kannada OCR": "2.ಕೇತದ ವಿವರಗಳು\nಭಾಗದ ಪ್ರದೇಶ:\n1. ಸಂಗಮ್‌ ರಸ್ತೆ 2. ಸಂಗಂಮ್‌್‌ ರಸ್ತೆ ಕಾಸ್‌ 3. IA,\nಬೀದಿ ಕ್ರಾಸ್‌\nಭಾಗದ ವರ್ಗೀಕರಣ: ನಗರ | ಈ ಭಾಗದಲ್ಲಿನ ಸಹಾಯಕ\nಮತಗಟ್ಟೆಗಳ ಸಂಖ್ಯೆ:\n3. ಮತಗಟ್ಟೆಯ ವಿವರಗಳು",
    "Source Image": "A0860074.png",
    "Official PDF URL": "https://ceo.karnataka.gov.in/uploads/BBMP/AC%2086/A0860074.pdf"
  },
  {
    "Part Number": "78",
    "Part Code": "A0860078",
    "Issue": "One first road name is unresolved",
    "Review Type": "Readable but unresolved / geocode not confirmed",
    "Raw Kannada OCR": "2.ಕತ್ರದ ವಿವರಗಳು\n\nಭಾಗದ ಪ್ರದೇಶ:\n\n1. ABA AF ರಸ್ತೆ 2. ಅಲಸೂರು ರಸ್ತೆ 3. ಎಂ.ಜಿ. ರಸ್ತೆ 4.\nಅನ್ನಸ್ವಾಂಮಿ ಮೊದಲಿಯಾರ್‌ ರಸ್ತೆ 5. ಸೇಂಟ್‌ ಜಾನ್ಸ ರಸ್ತೆ 6.ಕೆ.\nparler’ ಕ್ವಾರ್ಟಸ್‌ 7. ದೋೀಬಿ ಫಾಟ್‌\n\nಭಾಗದ ವರ್ಗೀಕರಣ: ನಗರ | ಈ ಭಾಗದಲಿನ ಸಹಾಯಕ\n\nಮತಗಟ್ಟೆಗಳ ಸಂಖ್ಯೆ:\n\nFy ds ded a",
    "Source Image": "A0860078.png",
    "Official PDF URL": "https://ceo.karnataka.gov.in/uploads/BBMP/AC%2086/A0860078.pdf"
  },
  {
    "Part Number": "79",
    "Part Code": "A0860079",
    "Issue": "One road name is unresolved",
    "Review Type": "Readable but unresolved / geocode not confirmed",
    "Raw Kannada OCR": "2.ಕೇತದ ವಿವರಗಳು\n\nಭಾಗದ ಪ್ರದೇಶ:\n\n1. ಗಂಗಾಧರ ಚೆಟ್ಟಿ ರಸ್ತೆ\n\n2. ಆಗಾ ಅಬ್ಬಾಸ್‌ ಆಲಿ ರಸ್ತೆ\n\n3. ear on\n\nಭಾಗದ ವರ್ಗೀಕರಣ: ನಗರ | ಈ ಭಾಗದಲಿನ ಸಹಾಯಕ\n\nಮತಗಟ್ಟೆಗಳ ಸಂಖ್ಯೆ:\n\nFy ds ded a",
    "Source Image": "A0860079.png",
    "Official PDF URL": "https://ceo.karnataka.gov.in/uploads/BBMP/AC%2086/A0860079.pdf"
  },
  {
    "Part Number": "80",
    "Part Code": "A0860080",
    "Issue": "A to D Blocks",
    "Review Type": "Readable but unresolved / geocode not confirmed",
    "Raw Kannada OCR": "2.ಕೇತದ ವಿವರಗಳು\nಭಾಗದ ಪ್ರದೇಶ:\n1. ಆರ್‌. ಕರ್ಟಿಸ್‌, ಎ ಇಂದ ಡಿ ಬಾಕ್‌\nಭಾಗದ ವರ್ಗೀಕರಣ: ನಗರ | ಈ ಭಾಗದಲಿನ ಸಹಾಯಕ\nಮತಗಟ್ಟೆಗಳ ಸಂಖ್ಯೆ:\n3. ಮತಗಟ್ಟೆಯ ವಿವರಗಳು",
    "Source Image": "A0860080.png",
    "Official PDF URL": "https://ceo.karnataka.gov.in/uploads/BBMP/AC%2086/A0860080.pdf"
  },
  {
    "Part Number": "81",
    "Part Code": "A0860081",
    "Issue": "Requires source/map review",
    "Review Type": "Readable but unresolved / geocode not confirmed",
    "Raw Kannada OCR": "2.ಕತ್ರದ ವಿವರಗಳು\nಭಾಗದ ಪ್ರದೇಶ:\n1. ಸೆಂಟ್‌ ಜಾಪ್ಸರಸೆ 2. a0 ಬೋರ್ಡ್‌ ಕ್ಲಾಟಿಸ್‌\nಭಾಗದ ವರ್ಗೀಕರಣ: ನಗರ | ಈ ಭಾಗದಲಿನ ಸಹಾಯಕ\nಮತಗಟ್ಟೆಗಳ ಸಂಖ್ಯೆ:\n3. ಮತಗಟ್ಟೆಯ ವಿವರಗಳು",
    "Source Image": "A0860081.png",
    "Official PDF URL": "https://ceo.karnataka.gov.in/uploads/BBMP/AC%2086/A0860081.pdf"
  },
  {
    "Part Number": "83",
    "Part Code": "A0860083",
    "Issue": "One road name is unresolved",
    "Review Type": "Readable but unresolved / geocode not confirmed",
    "Raw Kannada OCR": "2.ಕತ್ರದ ವಿವರಗಳು\nಭಾಗದ ಪ್ರದೇಶ:\n1. ಅಸ್‌ ಬಾರ್ನ್‌ ರಸ್ತೆ 2. oben) ಅವೆಮ್ಯೂ OA, 3.\nHOO 630,07 * OA\nಭಾಗದ ವರ್ಗೀಕರಣ: ನಗರ | ಈ ಭಾಗದಲಿನ ಸಹಾಯಕ\nಮತಗಟ್ಟೆಗಳ ಸಂಖ್ಯೆ:\n3. ಮತಗಟ್ಟೆಯ ವಿವರಗಳು",
    "Source Image": "A0860083.png",
    "Official PDF URL": "https://ceo.karnataka.gov.in/uploads/BBMP/AC%2086/A0860083.pdf"
  },
  {
    "Part Number": "86",
    "Part Code": "A0860086",
    "Issue": "One street name is unresolved",
    "Review Type": "Readable but unresolved / geocode not confirmed",
    "Raw Kannada OCR": "2.ಕತ್ರದ ವಿವರಗಳು\nಭಾಗದ ಪ್ರದೇಶ:\n1. ಯೆಲ್ಲಮ್ಮ ದೇವಸ್ಥಾನದ ಬೀದಿ ಎಫ್‌. ನಂ. 1ನೇ ಮತ್ತು 2ನೇ\nಬದಿ 2. ಅಲಸೂರು CO OAL, 3. Bete) ಬೇದಿ\nಭಾಗದ ವರ್ಗೀಕರಣ: ಸಗರ | ಈ ಭಾಗದಲ್ಲಿನ ಸಹಾಯಕ\nಮತಗಟ್ಟೆಗಳ ಸಂಖ್ಯೆ:\n3. ಮತಗಟ್ಟೆಯ ವಿವರಗಳು",
    "Source Image": "A0860086.png",
    "Official PDF URL": "https://ceo.karnataka.gov.in/uploads/BBMP/AC%2086/A0860086.pdf"
  },
  {
    "Part Number": "92",
    "Part Code": "A0860092",
    "Issue": "Source page missing from uploaded archive",
    "Review Type": "Missing source page",
    "Raw Kannada OCR": null,
    "Source Image": "Missing",
    "Official PDF URL": "https://ceo.karnataka.gov.in/uploads/BBMP/AC%2086/A0860092.pdf"
  },
  {
    "Part Number": "104",
    "Part Code": "A0860104",
    "Issue": "One 6th Cross reference is unclear",
    "Review Type": "Readable but unresolved / geocode not confirmed",
    "Raw Kannada OCR": "2.ಕತ್ರದ ವಿವರಗಳು\nಭಾಗದ ಪ್ರದೇಶ:\n\n1. Sale, 6ನೇ ಅಡ್ಡರಸ್ತೆ 2. ಎಸ್‌.ಬನ್‌.ಟಿ. ವಂ. 118, 119, 120,\nಅಲಸೂರು, ಸತ್ಯನಾರಾಯಣ ದೇವಸ್ಥಾನ ರಸ್ತೆ 3. ತಾಯಪ್ಪ\nಗಾರ್ಡನ್‌ 4. ದೊರೈ ಗಾರ್ಡನ್‌ 5. ವರದರಾಜ ಗಾರ್ಡನ್‌ 6.\nಮರೆ ಟೌನ್‌ ಎ ಬೀದಿ\n\nಭಾಗದ ವರ್ಗೀಕರಣ: ನಗರ | ಈ ಭಾಗದಲಿನ ಸಹಾಯಕ\n\nಮತಗಟ್ಟೆಗಳ ಸಂಖ್ಯೆ:",
    "Source Image": "A0860104.png",
    "Official PDF URL": "https://ceo.karnataka.gov.in/uploads/BBMP/AC%2086/A0860104.pdf"
  },
  {
    "Part Number": "106",
    "Part Code": "A0860106",
    "Issue": "One Jayaraj Nagar street identifier is unclear",
    "Review Type": "Readable but unresolved / geocode not confirmed",
    "Raw Kannada OCR": "2.ಕತ್ರದ ವಿವರಗಳು\nಭಾಗದ ಪ್ರದೇಶ:\n1. ಜಯರಾಜ್‌ ವಗರ ಹೆಜ್‌ ಸ್ಟ್ರೀಟ್‌ 2. ಜಯರಾಜವಗರ Ao 3.\nಗ್ಯಾಂಗ್‌ ಮವ್‌ ಕ್ಬಾರ್ಟಿಸ್‌\nಭಾಗದ ವರ್ಗೀಕರಣ: ನಗರ | ಈ ಭಾಗದಲಿನ ಸಹಾಯಕ\nಮತಗಟ್ಟೆಗಳ ಸಂಖ್ಯೆ:\n3. ಮತಗಟ್ಟೆಯ ವಿವರಗಳು",
    "Source Image": "A0860106.png",
    "Official PDF URL": "https://ceo.karnataka.gov.in/uploads/BBMP/AC%2086/A0860106.pdf"
  },
  {
    "Part Number": "111",
    "Part Code": "A0860111",
    "Issue": "Sadashiva Mudaliar Road 6th and 7th Crosses; Murphy Town 7th and 9th Crosses; one final fragment is illegible",
    "Review Type": "Illegible / insufficient OCR",
    "Raw Kannada OCR": "2.ಕೇತದ ವಿವರಗಳು\nಭಾಗದ ಪ್ರದೇಶ:\n\n1. ಸದಾಶಿವ ಮೊದಲಿಯಾರ್‌ ರಸ್ತೆ, 6, 7ನೇ ಕಾಸ್‌, 2.\nಮಫಿಟೌನ್‌ 7ನೇಕಾಸ್‌ ಮತ್ತು 9ನೇ ಕ್ರಾಸ್‌, 3. ಗ್ಯಾಂಗ್‌ಮನ್‌\nಕ್ಲಾಟಿಸ್‌, 4. ಬಿ\n\nಭಾಗದ ವರ್ಗೀಕರಣ: ನಗರ | ಈ ಭಾಗದಲಿನ ಸಹಾಯಕ\n\nಮತಗಟ್ಟೆಗಳ ಸಂಖ್ಯೆ:\nFy ds ded a",
    "Source Image": "A0860111.png",
    "Official PDF URL": "https://ceo.karnataka.gov.in/uploads/BBMP/AC%2086/A0860111.pdf"
  },
  {
    "Part Number": "120",
    "Part Code": "A0860120",
    "Issue": "1st to 7th numbered roads; Main/Cross wording requires source recheck",
    "Review Type": "Readable but unresolved / geocode not confirmed",
    "Raw Kannada OCR": "2.ಕೇತದ ವಿವರಗಳು\nಭಾಗದ ಪ್ರದೇಶ:\n\n1. Tait ಮುಖ್ಯರಸ್ತೆ, ಐಲ್‌. ಎಸ್‌. ವಗರ\n2, 2ವೇ ಮುಖ್ಯರಸ್ತೆ, ಎಲ್‌.ಬಿ.ಎಸ್‌. ವಗರ\n3. 3ನೇ ಮುಖ್ಯರಸ್ತೆ, ಐಲ್‌.ಬೆ.ಎಸ್‌. ವಗರ\n4, dag ಮುಖ್ಯರಸ್ತೆ, ಕಖುಲ್‌.ಬೆ.ಎಸ್‌. ವಗರ\n5. Saif 978 DAL, ಐಬ್‌.ಬಿ.ಎಸ್‌. ವಗರ\n6. 7ವೇ SOA, ಐಲ್‌.ಐಬಿ.ಎಸ್‌. ವಗರ\n\npid pel mm cre A eit tee",
    "Source Image": "A0860120.png",
    "Official PDF URL": "https://ceo.karnataka.gov.in/uploads/BBMP/AC%2086/A0860120.pdf"
  },
  {
    "Part Number": "126",
    "Part Code": "A0860126",
    "Issue": "Multiple numbered Main and Cross Roads; exact sequence retained in raw OCR",
    "Review Type": "Readable but unresolved / geocode not confirmed",
    "Raw Kannada OCR": "2.ಕೇತದ ವಿವರಗಳು\nಭಾಗದ ಪ್ರದೇಶ:\n\n1. 100 ಅಡಿರಸ್ತೆ, 2.00. 1ನೇ ಹಂತ, 1,2,7, 6, 4, 5, Baie\nಅಡರಸ್ತೆ, 1,2, 4, 5, 6, 7, 8ನೇ ಅಡ್ಡರಸ್ತೆ, ಬಿನ್ನಮಂಗಲ 1ನೇ\nmos\n\nಭಾಗದ ವರ್ಗೀಕರಣ: ನಗರ | ಈ ಭಾಗದಲಿನ ಸಹಾಯಕ\n\nಮತಗಟ್ಟೆಗಳ ಸಂಖ್ಯೆ:\nFy ds ded a",
    "Source Image": "A0860126.png",
    "Official PDF URL": "https://ceo.karnataka.gov.in/uploads/BBMP/AC%2086/A0860126.pdf"
  },
  {
    "Part Number": "128",
    "Part Code": "A0860128",
    "Issue": "1st, 6th, 7th, 10th, 11th and 12th Cross Roads",
    "Review Type": "Readable but unresolved / geocode not confirmed",
    "Raw Kannada OCR": "2.ಕತ್ರದ ವಿವರಗಳು\nಭಾಗದ ಪ್ರದೇಶ:\n\n1.10,11,12,1, 6, 7, ವೇ ಅಡ್ಣರಸ್ತೆ ಇಂದಿರಾನಗರ 1ನೇ ಹಂತ\n2.100 ಆಡಿ ರಸ್ತೆ, ಇಂದಿರಾನಗರ 1ನೇ ಹಂತ\n3. ಸಿ. ಎಂ.ಹೆಚ್‌ ರಸ್ತೆ, 100 ಆಡಿ ರಸ್ತೆ, ದ್ವಾರಕಾ\nಅಪಾರ್ಟಮೆಂಟ್‌ ರಮಾರಿಜಾಯ್‌್ಸ\nಅಪಾರ್ಟಮೆಂಟ್‌\n\nಭಾಗದ ವರ್ಗೀಕರಣ: ನಗರ | ಈ ಭಾಗದಲ್ಲಿನ ಸಹಾಯಕ |\n\n~~ aA fet tas.",
    "Source Image": "A0860128.png",
    "Official PDF URL": "https://ceo.karnataka.gov.in/uploads/BBMP/AC%2086/A0860128.pdf"
  },
  {
    "Part Number": "134",
    "Part Code": "A0860134",
    "Issue": "Final road/locality suffix is faint; no pin assigned",
    "Review Type": "Readable but unresolved / geocode not confirmed",
    "Raw Kannada OCR": "2.ಕೇತದ ವಿವರಗಳು\nಭಾಗದ ಪ್ರದೇಶ:\n1. ಹೊಸ ಬಿಷ್ಪಮಂಗಲ ART\nಭಾಗದ ವರ್ಗೀಕರಣ: ನಗರ | ಈ ಭಾಗದಲ್ಲಿನ ಸಹಾಯಕ\nಮತಗಟ್ಟೆಗಳ ಸಂಖ್ಯೆ:\n3. ಮತಗಟ್ಟೆಯ ವಿವರಗಳು",
    "Source Image": "A0860134.png",
    "Official PDF URL": "https://ceo.karnataka.gov.in/uploads/BBMP/AC%2086/A0860134.pdf"
  }
]